{"MATERIAL":"corrugated metal/heavily patched","AVG_SLOPE":5.74800777199,"AVG_HEIGHT":3.21738991493,"TERAIN_SLP":3.55149152022,"AREA":58.7642260843,"VOLUME":189,"FLOORS":2,"INT_ZONE":"Borde Rural","FLOOD":1,"LANDSLIDE":"Amenaza Media","LEGAL_ID":"311","LEGAL_NAME":"EL MIRADOR","LEGAL_AREA":11.06,"LEGAL_LOTS":989,"LEGAL_POP":5340.6,"LEGAL_DENS":89.42,"LEGALIZING":null,"BLOCK_ID_":"002570073","BLOCK_POP":88,"BLOCK_BLD":24,"BLOCK_RISK":8.0373611,"BLOCK_EDU":0,"BLOCK_HLTH":9.0482588,"BLOCK_TRAN":98.988823,"BLOCK_CULT":0,"BLOCK_PARK":31.617407,"BLOCK_SEC":100,"BLOCK_CENT":0,"BLOCK_DEF":29.1666666667,"BLD_INHAB":4,"OBJECTID":1,"AO_225":0.16,"id":1478,"images":[]}
