{"MATERIAL":"corrugated metal","AVG_SLOPE":6.10327303682,"AVG_HEIGHT":2.80304634065,"TERAIN_SLP":6.20994692786,"AREA":24.3234976707,"VOLUME":68,"FLOORS":1,"INT_ZONE":null,"FLOOD":2,"LANDSLIDE":"Amenaza Media","LEGAL_ID":null,"LEGAL_NAME":null,"LEGAL_AREA":0,"LEGAL_LOTS":0,"LEGAL_POP":0,"LEGAL_DENS":0,"LEGALIZING":"No viable","BLOCK_ID_":"204106026","BLOCK_POP":7,"BLOCK_BLD":2,"BLOCK_RISK":1.3398358,"BLOCK_EDU":81.804642,"BLOCK_HLTH":0,"BLOCK_TRAN":95.833717,"BLOCK_CULT":0,"BLOCK_PARK":0,"BLOCK_SEC":100,"BLOCK_CENT":0,"BLOCK_DEF":50,"BLD_INHAB":4,"OBJECTID":2,"AO_225":0.2,"id":4102,"images":[]}
