{"MATERIAL":"corrugated metal","AVG_SLOPE":4.83836367363,"AVG_HEIGHT":1.33567417275,"TERAIN_SLP":28.1435967042,"AREA":56.375783571,"VOLUME":75,"FLOORS":1,"INT_ZONE":null,"FLOOD":1,"LANDSLIDE":"Amenaza Media","LEGAL_ID":"231","LEGAL_NAME":"BELLA FLOR","LEGAL_AREA":24.13,"LEGAL_LOTS":1732,"LEGAL_POP":9352.8,"LEGAL_DENS":71.77786987,"LEGALIZING":null,"BLOCK_ID_":"002580060","BLOCK_POP":90,"BLOCK_BLD":23,"BLOCK_RISK":18.20948,"BLOCK_EDU":0,"BLOCK_HLTH":0,"BLOCK_TRAN":95.109055,"BLOCK_CULT":0,"BLOCK_PARK":99.627869,"BLOCK_SEC":100,"BLOCK_CENT":0,"BLOCK_DEF":52.1739130435,"BLD_INHAB":4,"OBJECTID":1,"AO_225":0.16,"id":5500,"images":[]}
